inori/__init__.py
inori/client.py
inori/logging.py
inori/route.py
inori/version.py
inori/utils/__init__.py
inori/utils/headerdict.py
inori/utils/sanitize.py
inori/utils/string_template.py
inori-0.0.15.dist-info/LICENSE
inori-0.0.15.dist-info/METADATA
inori-0.0.15.dist-info/WHEEL
inori-0.0.15.dist-info/top_level.txt
inori-0.0.15.dist-info/RECORD
