Metadata-Version: 2.1
Name: inori
Version: 0.0.15
Summary: The Universal API Client Constructor.
Home-page: https://github.com/jsfehler/inori
Author: Joshua Fehler
License: GPLv3
Classifier: Programming Language :: Python :: 3.8
Classifier: Programming Language :: Python :: 3.9
Classifier: Programming Language :: Python :: 3.10
Classifier: Programming Language :: Python :: 3.11
Classifier: Programming Language :: Python :: 3.12
Classifier: License :: OSI Approved :: GNU General Public License v3 (GPLv3)
Classifier: Operating System :: OS Independent
Classifier: Development Status :: 4 - Beta
License-File: LICENSE
Requires-Dist: requests >=2.26.0
Requires-Dist: shibari >=0.0.2
